qcore-1.11.1.dist-info/top_level.txt
qcore-1.11.1.dist-info/RECORD
qcore-1.11.1.dist-info/LICENSE
qcore-1.11.1.dist-info/METADATA
qcore-1.11.1.dist-info/WHEEL
qcore/events.py
qcore/errors.py
qcore/asserts.py
qcore/decorators.cpython-313-i386-linux-gnu.so
qcore/helpers.py
qcore/helpers.cpython-313-i386-linux-gnu.so
qcore/events.pxd
qcore/inspection.cpython-313-i386-linux-gnu.so
qcore/debug.pyi
qcore/helpers.pxd
qcore/inspectable_class.pyi
qcore/asserts.pyi
qcore/microtime.py
qcore/debug.py
qcore/testing.pyi
qcore/caching.cpython-313-i386-linux-gnu.so
qcore/inspectable_class.py
qcore/errors.pyi
qcore/events.pyi
qcore/caching.py
qcore/__init__.py
qcore/enum.pyi
qcore/events.cpython-313-i386-linux-gnu.so
qcore/inspection.pyi
qcore/disallow_inheritance.py
qcore/disallow_inheritance.pyi
qcore/inspection.py
qcore/inspection.pxd
qcore/decorators.pyi
qcore/caching.pyi
qcore/enum.py
qcore/microtime.cpython-313-i386-linux-gnu.so
qcore/microtime.pxd
qcore/caching.pxd
qcore/testing.py
qcore/microtime.pyi
qcore/decorators.pxd
qcore/__init__.pyi
qcore/decorators.py
qcore/helpers.pyi
qcore/py.typed
qcore/tests/test_testing.py
qcore/tests/test_disallow_inheritance.py
qcore/tests/test_events.py
qcore/tests/test_errors.py
qcore/tests/test_enum.py
qcore/tests/test_decorators.py
qcore/tests/test_helpers.py
qcore/tests/test_inspectable_class.py
qcore/tests/test_asserts.py
qcore/tests/test_inspection.py
qcore/tests/test_examples.py
qcore/tests/test_microtime.py
qcore/tests/test_debug.py
qcore/tests/test_caching.py
