Metadata-Version: 2.1
Name: qcore
Version: 1.11.1
Home-page: https://github.com/quora/qcore
Author-email: "Quora, Inc." <asynq@quora.com>
License: Apache Software License
Keywords: quora,core,common,utility
Classifier: License :: OSI Approved :: Apache Software License
Classifier: Programming Language :: Python
Classifier: Programming Language :: Python :: 3.9
Classifier: Programming Language :: Python :: 3.10
Classifier: Programming Language :: Python :: 3.11
Classifier: Programming Language :: Python :: 3.12
Classifier: Programming Language :: Python :: 3.13
Requires-Python: >=3.9
License-File: LICENSE
